{
  "is_kennedy_assassination": true,
  "important": true,
  "title": "ジョン・F・ケネディ暗殺に関するユリ・イワノビッチ・ノセンコのファイル",
  "summary": "# ユリ・イワノビッチ・ノセンコに関する情報\n\n- **内容**: ノセンコに関する約3600ページのインタビュー、トランスクリプト、メモ、報告書が含まれている。\n- **公開状況**: 約1200ページが公開され、そのうち約800ページはリー・ハーヴェイ・オズワルドおよびケネディ大統領の暗殺に直接関連する情報を含む。\n- **処理状況**: 残りの2400ページはケネディ暗殺に関連しないと判断され、別の処理が必要。\n- **ノセンコの信頼性**: 1968年のソリ報告書がノセンコの信頼性を再確認している。",
  "page_info": {
    "total_pages": 76,
    "analyzed_pages": 30,
    "note": "ページ数が30を超えるため、最初の30ページのみを分析しました"
  }
}